dndbeyond_websearch/__init__.py
dndbeyond_websearch-0.1.dist-info/DESCRIPTION.rst
dndbeyond_websearch-0.1.dist-info/METADATA
dndbeyond_websearch-0.1.dist-info/RECORD
dndbeyond_websearch-0.1.dist-info/WHEEL
dndbeyond_websearch-0.1.dist-info/metadata.json
dndbeyond_websearch-0.1.dist-info/top_level.txt
