Metadata-Version: 2.0
Name: dndbeyond-websearch
Version: 0.1
Summary: Search via dndbeyond.com built-in search
Home-page: https://github.com/VadimPushtaev/dndbeyond_websearch
Author: Vadim Pushtaev
Author-email: pushtaev.vm@gmail.com
License: MIT
Platform: UNKNOWN
Requires-Dist: requests
Requires-Dist: beautifulsoup4
